pathmodel/__init__.py
pathmodel/__main__.py
pathmodel/pathmodel_wrapper.py
pathmodel/plotting.py
pathmodel/asp/CompareMolecules.lp
pathmodel/asp/MZComputation.lp
pathmodel/asp/PathModel.lp
pathmodel/asp/ReactionSiteExtraction.lp
pathmodel/data/MAA_pwy.lp
pathmodel/data/brown_sterols_pwy.lp
pathmodel/data/mozukulins_pwy.lp
pathmodel/data/sterol_pwy.lp
pathmodel-0.2.1.dist-info/METADATA
pathmodel-0.2.1.dist-info/WHEEL
pathmodel-0.2.1.dist-info/entry_points.txt
pathmodel-0.2.1.dist-info/top_level.txt
pathmodel-0.2.1.dist-info/RECORD
