Metadata-Version: 2.1
Name: pathmodel
Version: 0.2.1
Summary: Ab initio pathway inference
Home-page: https://github.com/pathmodel/pathmodel
Author: A. Belcour
Author-email: UNKNOWN
License: UNKNOWN
Platform: UNKNOWN
Requires-Dist: clyngor
Requires-Dist: matplotlib
Requires-Dist: clyngor-with-clingo
Requires-Dist: networkx
